collective.schedulefield-1.1-py3.12-nspkg.pth
collective/schedulefield/__init__.py
collective/schedulefield/behavior.py
collective/schedulefield/configure.zcml
collective/schedulefield/exceptionalclosure.py
collective/schedulefield/exceptionalclosure_content_viewlet.pt
collective/schedulefield/exceptionalclosure_display.pt
collective/schedulefield/interfaces.py
collective/schedulefield/multi_scheduled_content_viewlet.pt
collective/schedulefield/schedule.py
collective/schedulefield/schedule_display.pt
collective/schedulefield/schedule_hidden.pt
collective/schedulefield/schedule_input.pt
collective/schedulefield/scheduled_content_viewlet.pt
collective/schedulefield/schedulewithtitle_display.pt
collective/schedulefield/serializer.py
collective/schedulefield/testing.py
collective/schedulefield/utils.py
collective/schedulefield/viewlet.py
collective/schedulefield/js/jquery.maskedinput.min.js
collective/schedulefield/js/schedulemask.js
collective/schedulefield/locales/collective.schedulefield.pot
collective/schedulefield/locales/update.sh
collective/schedulefield/locales/en/LC_MESSAGES/collective.schedulefield.po
collective/schedulefield/locales/fr/LC_MESSAGES/collective.schedulefield.po
collective/schedulefield/profiles/default/browserlayer.xml
collective/schedulefield/profiles/default/collectiveschedulefield_default.txt
collective/schedulefield/profiles/default/metadata.xml
collective/schedulefield/profiles/uninstall/browserlayer.xml
collective/schedulefield/static/schedulefield.css
collective_schedulefield-1.1.dist-info/licenses/LICENSE.GPL
collective_schedulefield-1.1.dist-info/licenses/LICENSE.rst
collective_schedulefield-1.1.dist-info/METADATA
collective_schedulefield-1.1.dist-info/WHEEL
collective_schedulefield-1.1.dist-info/entry_points.txt
collective_schedulefield-1.1.dist-info/namespace_packages.txt
collective_schedulefield-1.1.dist-info/top_level.txt
collective_schedulefield-1.1.dist-info/RECORD
